COPYING
MANIFEST.in
README.md
setup.py
crocodile/__init__.py
crocodile/__init__.pyc
crocodile/templatetags/__init__.py
crocodile/templatetags/__init__.pyc
crocodile/templatetags/crocodile.py
crocodile/templatetags/crocodile.pyc
django_crocodile.egg-info/PKG-INFO
django_crocodile.egg-info/SOURCES.txt
django_crocodile.egg-info/dependency_links.txt
django_crocodile.egg-info/requires.txt
django_crocodile.egg-info/top_level.txt