Metadata-Version: 1.1
Name: django-crocodile
Version: 0.4.1
Summary: A simple CSS and Javascript aggregator for Django
Home-page: https://github.com/danielquinn/django-crocodile
Author: Daniel Quinn
Author-email: code@danielquinn.org
License: GPLv3
Download-URL: https://github.com/danielquinn/django-crocodile
Platform: UNKNOWN
Classifier: Development Status :: 4 - Beta
Classifier: Environment :: Web Environment
Classifier: Framework :: Django
Classifier: Intended Audience :: Developers
Classifier: License :: OSI Approved :: GNU General Public License v3 or later (GPLv3+)
Classifier: Operating System :: POSIX
Classifier: Operating System :: Unix
Classifier: Programming Language :: Python
Classifier: Programming Language :: Python :: 2.6
Classifier: Programming Language :: Python :: 2.7
Classifier: Topic :: Internet :: WWW/HTTP
Classifier: Topic :: Internet :: WWW/HTTP :: Dynamic Content
